{
  "article_id": "554400000287675",
  "alternate_id": null,
  "source_type": "va_manual",
  "source_system": "knowva.ebenefits.va.gov",
  "source_url": "https://www.knowva.ebenefits.va.gov/system/templates/selfservice/va_ssnew/help/customer/locale/en-US/portal/554400000001018/content/554400000287675",
  "topic_breadcrumb": [
    "M22-4",
    "Part 02 – Computer Processing",
    "03 - Benefits Manager"
  ],
  "topic_id": "554400000016141",
  "manual_name": "M22-4",
  "title": "M22-4, Part II, Chapter 3, Section A – General Benefits Manager Information",
  "description": "This part discusses how non-chapter 33 education benefits, Montgomery GI Bill (MGIB or chapter 30), Montgomery GI Bill - Selected Reserve (chapter 1606), and Survivors' and Dependents' Educational Assistance (DEA or chapter 35) are processed in Benefits Manager (BM).",
  "last_modified": "2025-08-27T18:14:25.000Z",
  "created": "2024-11-15T18:27:18Z",
  "version": "55",
  "state": "P",
  "contains_table": true,
  "contains_list": true,
  "heading_outline": [
    {
      "level": 1,
      "text": "M22-4, Part II, Chapter 3, Section A – General Benefits Manager Information"
    }
  ],
  "heading_count": 1,
  "content_category": "gov_docs_and_manuals",
  "target_audience": "",
  "process_change": "",
  "attachments": [],
  "acl": "public",
  "source_authority_tier": 1
}