{
  "article_id": "554400000076342",
  "alternate_id": null,
  "source_type": "va_manual",
  "source_system": "knowva.ebenefits.va.gov",
  "source_url": "https://www.knowva.ebenefits.va.gov/system/templates/selfservice/va_ssnew/help/customer/locale/en-US/portal/554400000001018/content/554400000076342",
  "topic_breadcrumb": [
    "M22-4",
    "Part 05 – Chapter 30",
    "11 – Accelerated Payment"
  ],
  "topic_id": "554400000016190",
  "manual_name": "M22-4",
  "title": "Part 5: Chapter 11 - Accelerated Payment",
  "description": "This article provides guidance and information in regards to the processing of accelerated payments.",
  "keywords": "chapter 30, MGIB, High Tech, lump sum, accelerated, enrollment, certify, term, charges, tuition, letter, break",
  "last_modified": "2018-03-13T20:56:51.000Z",
  "created": "2018-01-04T22:15:44Z",
  "version": "8",
  "state": "P",
  "contains_table": true,
  "contains_list": true,
  "heading_outline": [
    {
      "level": 2,
      "text": "11.06 RESERVED(Change Date:  April 28, 2008)"
    }
  ],
  "heading_count": 1,
  "content_category": "",
  "target_audience": "",
  "process_change": "",
  "attachments": []
}